[
  {
    "name": "app",
    "path": "src/app",
    "sha": "65bc796a94dfd318a25660f4b79442bd331633ff",
    "size": 0,
    "url": "https://api.github.com/repos/VoltisLabs/voltislabs.com/contents/src/app?ref=main",
    "html_url": "https://github.com/VoltisLabs/voltislabs.com/tree/main/src/app",
    "git_url": "https://api.github.com/repos/VoltisLabs/voltislabs.com/git/trees/65bc796a94dfd318a25660f4b79442bd331633ff",
    "download_url": null,
    "type": "dir",
    "_links": {
      "self": "https://api.github.com/repos/VoltisLabs/voltislabs.com/contents/src/app?ref=main",
      "git": "https://api.github.com/repos/VoltisLabs/voltislabs.com/git/trees/65bc796a94dfd318a25660f4b79442bd331633ff",
      "html": "https://github.com/VoltisLabs/voltislabs.com/tree/main/src/app"
    }
  },
  {
    "name": "components",
    "path": "src/components",
    "sha": "981e16e6a7b674932a2e39b9669df8d2c4c0c096",
    "size": 0,
    "url": "https://api.github.com/repos/VoltisLabs/voltislabs.com/contents/src/components?ref=main",
    "html_url": "https://github.com/VoltisLabs/voltislabs.com/tree/main/src/components",
    "git_url": "https://api.github.com/repos/VoltisLabs/voltislabs.com/git/trees/981e16e6a7b674932a2e39b9669df8d2c4c0c096",
    "download_url": null,
    "type": "dir",
    "_links": {
      "self": "https://api.github.com/repos/VoltisLabs/voltislabs.com/contents/src/components?ref=main",
      "git": "https://api.github.com/repos/VoltisLabs/voltislabs.com/git/trees/981e16e6a7b674932a2e39b9669df8d2c4c0c096",
      "html": "https://github.com/VoltisLabs/voltislabs.com/tree/main/src/components"
    }
  }
]
